SnapChatBot/__init__.py
SnapChatBot/cli.py
SnapChatBot/cli_commands.py
SnapChatBot/exceptions.py
SnapChatBot/functions.py
SnapChatBot/main.py
SnapChatBot/snapchat.py
SnapChatBot/snapfunctions.py
SnapChatBot-1.0.3.dist-info/METADATA
SnapChatBot-1.0.3.dist-info/WHEEL
SnapChatBot-1.0.3.dist-info/top_level.txt
SnapChatBot-1.0.3.dist-info/RECORD
